{
    "len_A": 9,
    "len_B": 5,
    "coupled_A": 0,
    "coupled_B": 0,
    "covered_A_percent": 64.28571428571429,
    "covered_B_percent": 35.714285714285715,
    "covered_both_percent": 0.0,
    "World Water Forum in Senegal: only one in four Africans has access to drinking water": {
        "Mariupol: 'We have wounded and dead inside the bunkers'": {
            "are_similar": false,
            "similarity_percentage": 52.65344606416969,
            "polarity_X": 0.13472222222222222,
            "subjectivity_X": 0.6429292929292929,
            "polarity_Y": -0.03131012506012507,
            "subjectivity_Y": 0.26626984126984127,
            "simil_concepts": []
        },
        "Ukraine round-up: Putin backs off Mariupol storming": {
            "are_similar": false,
            "similarity_percentage": 53.67689028361453,
            "polarity_X": 0.13472222222222222,
            "subjectivity_X": 0.6429292929292929,
            "polarity_Y": -0.013334830787660982,
            "subjectivity_Y": 0.10411799940101829,
            "simil_concepts": []
        },
        "Images suggest mass graves dug near Mariupol": {
            "are_similar": false,
            "similarity_percentage": 57.796811172655595,
            "polarity_X": 0.13472222222222222,
            "subjectivity_X": 0.6429292929292929,
            "polarity_Y": 0.06737331296154826,
            "subjectivity_Y": 0.23885175282234106,
            "simil_concepts": []
        },
        "Honduran ex-leader extradited to US on drug charges": {
            "are_similar": false,
            "similarity_percentage": 57.20901113880033,
            "polarity_X": 0.13472222222222222,
            "subjectivity_X": 0.6429292929292929,
            "polarity_Y": -0.009103277674706247,
            "subjectivity_Y": 0.13846526489383634,
            "simil_concepts": []
        },
        "Kardashians deny faking Roblox sex tape scene": {
            "are_similar": false,
            "similarity_percentage": 61.82602976357152,
            "polarity_X": 0.13472222222222222,
            "subjectivity_X": 0.6429292929292929,
            "polarity_Y": 0.036312137942572716,
            "subjectivity_Y": 0.14677180709789406,
            "simil_concepts": []
        }
    },
    "Cyril Dion, writer: \"The ecological question is the great cause of the twenty-first century\"": {
        "Mariupol: 'We have wounded and dead inside the bunkers'": {
            "are_similar": false,
            "similarity_percentage": 0,
            "polarity_X": 0.2733333333333334,
            "subjectivity_X": 0.3583333333333334,
            "polarity_Y": -0.03131012506012507,
            "subjectivity_Y": 0.26626984126984127,
            "simil_concepts": []
        },
        "Ukraine round-up: Putin backs off Mariupol storming": {
            "are_similar": false,
            "similarity_percentage": 0,
            "polarity_X": 0.2733333333333334,
            "subjectivity_X": 0.3583333333333334,
            "polarity_Y": -0.013334830787660982,
            "subjectivity_Y": 0.10411799940101829,
            "simil_concepts": []
        },
        "Images suggest mass graves dug near Mariupol": {
            "are_similar": false,
            "similarity_percentage": 0,
            "polarity_X": 0.2733333333333334,
            "subjectivity_X": 0.3583333333333334,
            "polarity_Y": 0.06737331296154826,
            "subjectivity_Y": 0.23885175282234106,
            "simil_concepts": []
        },
        "Honduran ex-leader extradited to US on drug charges": {
            "are_similar": false,
            "similarity_percentage": 0,
            "polarity_X": 0.2733333333333334,
            "subjectivity_X": 0.3583333333333334,
            "polarity_Y": -0.009103277674706247,
            "subjectivity_Y": 0.13846526489383634,
            "simil_concepts": []
        },
        "Kardashians deny faking Roblox sex tape scene": {
            "are_similar": false,
            "similarity_percentage": 0,
            "polarity_X": 0.2733333333333334,
            "subjectivity_X": 0.3583333333333334,
            "polarity_Y": 0.036312137942572716,
            "subjectivity_Y": 0.14677180709789406,
            "simil_concepts": []
        }
    },
    "L'actu en dessin : le Giec Alert sur le climat ? So you have to \"suppress the Giec\"": {
        "Mariupol: 'We have wounded and dead inside the bunkers'": {
            "are_similar": false,
            "similarity_percentage": 50.208405463395145,
            "polarity_X": -0.17062413349178054,
            "subjectivity_X": 0.3246300540418187,
            "polarity_Y": -0.03131012506012507,
            "subjectivity_Y": 0.26626984126984127,
            "simil_concepts": []
        },
        "Ukraine round-up: Putin backs off Mariupol storming": {
            "are_similar": false,
            "similarity_percentage": 51.94873444287463,
            "polarity_X": -0.17062413349178054,
            "subjectivity_X": 0.3246300540418187,
            "polarity_Y": -0.013334830787660982,
            "subjectivity_Y": 0.10411799940101829,
            "simil_concepts": []
        },
        "Images suggest mass graves dug near Mariupol": {
            "are_similar": false,
            "similarity_percentage": 50.496253081341834,
            "polarity_X": -0.17062413349178054,
            "subjectivity_X": 0.3246300540418187,
            "polarity_Y": 0.06737331296154826,
            "subjectivity_Y": 0.23885175282234106,
            "simil_concepts": []
        },
        "Honduran ex-leader extradited to US on drug charges": {
            "are_similar": false,
            "similarity_percentage": 54.297150915466254,
            "polarity_X": -0.17062413349178054,
            "subjectivity_X": 0.3246300540418187,
            "polarity_Y": -0.009103277674706247,
            "subjectivity_Y": 0.13846526489383634,
            "simil_concepts": []
        },
        "Kardashians deny faking Roblox sex tape scene": {
            "are_similar": false,
            "similarity_percentage": 61.6498399879572,
            "polarity_X": -0.17062413349178054,
            "subjectivity_X": 0.3246300540418187,
            "polarity_Y": 0.036312137942572716,
            "subjectivity_Y": 0.14677180709789406,
            "simil_concepts": []
        }
    },
    "How can we explain the unprecedented heat cut in polar regions?": {
        "Mariupol: 'We have wounded and dead inside the bunkers'": {
            "are_similar": false,
            "similarity_percentage": 61.773850142259846,
            "polarity_X": 0.11981614171269343,
            "subjectivity_X": 0.4585734189182465,
            "polarity_Y": -0.03131012506012507,
            "subjectivity_Y": 0.26626984126984127,
            "simil_concepts": []
        },
        "Ukraine round-up: Putin backs off Mariupol storming": {
            "are_similar": false,
            "similarity_percentage": 67.19625482382443,
            "polarity_X": 0.11981614171269343,
            "subjectivity_X": 0.4585734189182465,
            "polarity_Y": -0.013334830787660982,
            "subjectivity_Y": 0.10411799940101829,
            "simil_concepts": []
        },
        "Images suggest mass graves dug near Mariupol": {
            "are_similar": false,
            "similarity_percentage": 64.48581631540776,
            "polarity_X": 0.11981614171269343,
            "subjectivity_X": 0.4585734189182465,
            "polarity_Y": 0.06737331296154826,
            "subjectivity_Y": 0.23885175282234106,
            "simil_concepts": []
        },
        "Honduran ex-leader extradited to US on drug charges": {
            "are_similar": false,
            "similarity_percentage": 66.78475332818324,
            "polarity_X": 0.11981614171269343,
            "subjectivity_X": 0.4585734189182465,
            "polarity_Y": -0.009103277674706247,
            "subjectivity_Y": 0.13846526489383634,
            "simil_concepts": []
        },
        "Kardashians deny faking Roblox sex tape scene": {
            "are_similar": false,
            "similarity_percentage": 70.92312436898376,
            "polarity_X": 0.11981614171269343,
            "subjectivity_X": 0.4585734189182465,
            "polarity_Y": 0.036312137942572716,
            "subjectivity_Y": 0.14677180709789406,
            "simil_concepts": []
        }
    },
    "According to the Giec, humanity has three years to reduce its CO2 emissions": {
        "Mariupol: 'We have wounded and dead inside the bunkers'": {
            "are_similar": false,
            "similarity_percentage": 61.79318707189474,
            "polarity_X": -0.05357431457431458,
            "subjectivity_X": 0.4079368286034953,
            "polarity_Y": -0.03131012506012507,
            "subjectivity_Y": 0.26626984126984127,
            "simil_concepts": []
        },
        "Ukraine round-up: Putin backs off Mariupol storming": {
            "are_similar": false,
            "similarity_percentage": 64.11033188004863,
            "polarity_X": -0.05357431457431458,
            "subjectivity_X": 0.4079368286034953,
            "polarity_Y": -0.013334830787660982,
            "subjectivity_Y": 0.10411799940101829,
            "simil_concepts": []
        },
        "Images suggest mass graves dug near Mariupol": {
            "are_similar": false,
            "similarity_percentage": 64.40408368072389,
            "polarity_X": -0.05357431457431458,
            "subjectivity_X": 0.4079368286034953,
            "polarity_Y": 0.06737331296154826,
            "subjectivity_Y": 0.23885175282234106,
            "simil_concepts": []
        },
        "Honduran ex-leader extradited to US on drug charges": {
            "are_similar": false,
            "similarity_percentage": 66.45682661848038,
            "polarity_X": -0.05357431457431458,
            "subjectivity_X": 0.4079368286034953,
            "polarity_Y": -0.009103277674706247,
            "subjectivity_Y": 0.13846526489383634,
            "simil_concepts": []
        },
        "Kardashians deny faking Roblox sex tape scene": {
            "are_similar": false,
            "similarity_percentage": 70.94547010168651,
            "polarity_X": -0.05357431457431458,
            "subjectivity_X": 0.4079368286034953,
            "polarity_Y": 0.036312137942572716,
            "subjectivity_Y": 0.14677180709789406,
            "simil_concepts": []
        }
    },
    "President: with Marine Le Pen in power, \"there would be no hope\" for the planet": {
        "Mariupol: 'We have wounded and dead inside the bunkers'": {
            "are_similar": false,
            "similarity_percentage": 65.72496533941504,
            "polarity_X": -0.00015408320493065972,
            "subjectivity_X": 0.185336414997432,
            "polarity_Y": -0.03131012506012507,
            "subjectivity_Y": 0.26626984126984127,
            "simil_concepts": []
        },
        "Ukraine round-up: Putin backs off Mariupol storming": {
            "are_similar": false,
            "similarity_percentage": 68.66454647695697,
            "polarity_X": -0.00015408320493065972,
            "subjectivity_X": 0.185336414997432,
            "polarity_Y": -0.013334830787660982,
            "subjectivity_Y": 0.10411799940101829,
            "simil_concepts": []
        },
        "Images suggest mass graves dug near Mariupol": {
            "are_similar": false,
            "similarity_percentage": 65.28394714819291,
            "polarity_X": -0.00015408320493065972,
            "subjectivity_X": 0.185336414997432,
            "polarity_Y": 0.06737331296154826,
            "subjectivity_Y": 0.23885175282234106,
            "simil_concepts": []
        },
        "Honduran ex-leader extradited to US on drug charges": {
            "are_similar": false,
            "similarity_percentage": 70.3460843589005,
            "polarity_X": -0.00015408320493065972,
            "subjectivity_X": 0.185336414997432,
            "polarity_Y": -0.009103277674706247,
            "subjectivity_Y": 0.13846526489383634,
            "simil_concepts": []
        },
        "Kardashians deny faking Roblox sex tape scene": {
            "are_similar": false,
            "similarity_percentage": 74.1124869295557,
            "polarity_X": -0.00015408320493065972,
            "subjectivity_X": 0.185336414997432,
            "polarity_Y": 0.036312137942572716,
            "subjectivity_Y": 0.14677180709789406,
            "simil_concepts": []
        }
    },
    "The climate, big forgotten of the presidential campaign": {
        "Mariupol: 'We have wounded and dead inside the bunkers'": {
            "are_similar": false,
            "similarity_percentage": 0,
            "polarity_X": 0.03333333333333333,
            "subjectivity_X": 0.1412698412698413,
            "polarity_Y": -0.03131012506012507,
            "subjectivity_Y": 0.26626984126984127,
            "simil_concepts": []
        },
        "Ukraine round-up: Putin backs off Mariupol storming": {
            "are_similar": false,
            "similarity_percentage": 0,
            "polarity_X": 0.03333333333333333,
            "subjectivity_X": 0.1412698412698413,
            "polarity_Y": -0.013334830787660982,
            "subjectivity_Y": 0.10411799940101829,
            "simil_concepts": []
        },
        "Images suggest mass graves dug near Mariupol": {
            "are_similar": false,
            "similarity_percentage": 0,
            "polarity_X": 0.03333333333333333,
            "subjectivity_X": 0.1412698412698413,
            "polarity_Y": 0.06737331296154826,
            "subjectivity_Y": 0.23885175282234106,
            "simil_concepts": []
        },
        "Honduran ex-leader extradited to US on drug charges": {
            "are_similar": false,
            "similarity_percentage": 0,
            "polarity_X": 0.03333333333333333,
            "subjectivity_X": 0.1412698412698413,
            "polarity_Y": -0.009103277674706247,
            "subjectivity_Y": 0.13846526489383634,
            "simil_concepts": []
        },
        "Kardashians deny faking Roblox sex tape scene": {
            "are_similar": false,
            "similarity_percentage": 0,
            "polarity_X": 0.03333333333333333,
            "subjectivity_X": 0.1412698412698413,
            "polarity_Y": 0.036312137942572716,
            "subjectivity_Y": 0.14677180709789406,
            "simil_concepts": []
        }
    },
    "Renewable energy: Austria at the top of the fight in Europe for green electricity": {
        "Mariupol: 'We have wounded and dead inside the bunkers'": {
            "are_similar": false,
            "similarity_percentage": 19.092124175033433,
            "polarity_X": 0.0886111111111111,
            "subjectivity_X": 0.32888888888888895,
            "polarity_Y": -0.03131012506012507,
            "subjectivity_Y": 0.26626984126984127,
            "simil_concepts": []
        },
        "Ukraine round-up: Putin backs off Mariupol storming": {
            "are_similar": false,
            "similarity_percentage": 24.430729769417443,
            "polarity_X": 0.0886111111111111,
            "subjectivity_X": 0.32888888888888895,
            "polarity_Y": -0.013334830787660982,
            "subjectivity_Y": 0.10411799940101829,
            "simil_concepts": []
        },
        "Images suggest mass graves dug near Mariupol": {
            "are_similar": false,
            "similarity_percentage": 23.793242197609487,
            "polarity_X": 0.0886111111111111,
            "subjectivity_X": 0.32888888888888895,
            "polarity_Y": 0.06737331296154826,
            "subjectivity_Y": 0.23885175282234106,
            "simil_concepts": []
        },
        "Honduran ex-leader extradited to US on drug charges": {
            "are_similar": false,
            "similarity_percentage": 27.509200385317527,
            "polarity_X": 0.0886111111111111,
            "subjectivity_X": 0.32888888888888895,
            "polarity_Y": -0.009103277674706247,
            "subjectivity_Y": 0.13846526489383634,
            "simil_concepts": []
        },
        "Kardashians deny faking Roblox sex tape scene": {
            "are_similar": false,
            "similarity_percentage": 30.384703634201678,
            "polarity_X": 0.0886111111111111,
            "subjectivity_X": 0.32888888888888895,
            "polarity_Y": 0.036312137942572716,
            "subjectivity_Y": 0.14677180709789406,
            "simil_concepts": []
        }
    },
    "A drought in winter": {
        "Mariupol: 'We have wounded and dead inside the bunkers'": {
            "are_similar": false,
            "similarity_percentage": 60.02825431871456,
            "polarity_X": 0.1569404310966811,
            "subjectivity_X": 0.26450481000481,
            "polarity_Y": -0.03131012506012507,
            "subjectivity_Y": 0.26626984126984127,
            "simil_concepts": []
        },
        "Ukraine round-up: Putin backs off Mariupol storming": {
            "are_similar": false,
            "similarity_percentage": 61.2544461079927,
            "polarity_X": 0.1569404310966811,
            "subjectivity_X": 0.26450481000481,
            "polarity_Y": -0.013334830787660982,
            "subjectivity_Y": 0.10411799940101829,
            "simil_concepts": []
        },
        "Images suggest mass graves dug near Mariupol": {
            "are_similar": false,
            "similarity_percentage": 57.52978916918096,
            "polarity_X": 0.1569404310966811,
            "subjectivity_X": 0.26450481000481,
            "polarity_Y": 0.06737331296154826,
            "subjectivity_Y": 0.23885175282234106,
            "simil_concepts": []
        },
        "Honduran ex-leader extradited to US on drug charges": {
            "are_similar": false,
            "similarity_percentage": 62.52359925181163,
            "polarity_X": 0.1569404310966811,
            "subjectivity_X": 0.26450481000481,
            "polarity_Y": -0.009103277674706247,
            "subjectivity_Y": 0.13846526489383634,
            "simil_concepts": []
        },
        "Kardashians deny faking Roblox sex tape scene": {
            "are_similar": false,
            "similarity_percentage": 67.27916510859521,
            "polarity_X": 0.1569404310966811,
            "subjectivity_X": 0.26450481000481,
            "polarity_Y": 0.036312137942572716,
            "subjectivity_Y": 0.14677180709789406,
            "simil_concepts": []
        }
    }
}
